Metadata-Version: 2.1
Name: deploy4s
Version: 1.0.5
Summary: A deploy tools for CodeDeploy
Home-page: https://github.com/meanstrong/deploy4s
Author: pengmingqiang
Author-email: rockypengchina@outlook.com
Maintainer: pengmingqiang
Maintainer-email: rockypengchina@outlook.com
License: Apache 2.0
Platform: any
